py_tools/__init__.py
py_tools/chatbot/__init__.py
py_tools/chatbot/app_server.py
py_tools/chatbot/chatbot.py
py_tools/chatbot/factory.py
py_tools/connections/__init__.py
py_tools/connections/db/__init__.py
py_tools/connections/db/redis_client.py
py_tools/connections/db/mysql/__init__.py
py_tools/connections/db/mysql/client.py
py_tools/connections/db/mysql/orm_model.py
py_tools/connections/http/__init__.py
py_tools/connections/http/client.py
py_tools/connections/mq/__init__.py
py_tools/connections/mq/kafka_client.py
py_tools/connections/mq/rabbitmq_client.py
py_tools/connections/oss/__init__.py
py_tools/connections/oss/minio_client.py
py_tools/constants/__init__.py
py_tools/constants/const.py
py_tools/data_schemas/__init__.py
py_tools/data_schemas/time.py
py_tools/data_schemas/unit.py
py_tools/decorators/__init__.py
py_tools/decorators/base.py
py_tools/decorators/cache.py
py_tools/enums/__init__.py
py_tools/enums/base.py
py_tools/enums/error.py
py_tools/enums/feishu.py
py_tools/enums/http.py
py_tools/enums/pub_biz.py
py_tools/enums/time.py
py_tools/exceptions/__init__.py
py_tools/exceptions/base.py
py_tools/logging/__init__.py
py_tools/logging/base.py
py_tools/logging/default_logging_conf.py
py_tools/meta_cls/__init__.py
py_tools/meta_cls/base.py
py_tools/utils/__init__.py
py_tools/utils/async_util.py
py_tools/utils/excel_util.py
py_tools/utils/file_util.py
py_tools/utils/func_util.py
py_tools/utils/jwt_util.py
py_tools/utils/mask_util.py
py_tools/utils/re_util.py
py_tools/utils/serializer_util.py
py_tools/utils/time_util.py
py_tools/utils/tree_util.py
py_tools/utils/project_templates/__init__.py
py_tools/utils/project_templates/make_pro.py
py_tools/utils/project_templates/python_project/src/server.py
py_tools/utils/project_templates/python_project/src/constants/__init__.py
py_tools/utils/project_templates/python_project/src/dao/__init__.py
py_tools/utils/project_templates/python_project/src/dao/orm/manage/__init__.py
hui_tools-0.5.8.dist-info/LICENSE
hui_tools-0.5.8.dist-info/METADATA
hui_tools-0.5.8.dist-info/WHEEL
hui_tools-0.5.8.dist-info/entry_points.txt
hui_tools-0.5.8.dist-info/top_level.txt
hui_tools-0.5.8.dist-info/RECORD
