Metadata-Version: 2.1
Name: hui-tools
Version: 0.5.8
Home-page: https://github.com/HuiDBK/py-tools
Author: hui
Author-email: huidbk@163.com
License: Apache
Classifier: Programming Language :: Python :: 3
Classifier: License :: OSI Approved :: Apache Software License
Classifier: Operating System :: OS Independent
Requires-Python: >=3.8
License-File: LICENSE
Requires-Dist: loguru <0.8,>=0.7.0
Requires-Dist: pydantic <3,>=2.1.1
Requires-Dist: asgiref ==3.8.1
Requires-Dist: nest-asyncio ==1.6.0
Requires-Dist: tqdm ==4.66.4
Requires-Dist: python-dateutil ==2.8.2
Requires-Dist: requests ==2.31.0
Requires-Dist: aiohttp ==3.9.5
Requires-Dist: cacheout ==0.14.1
Requires-Dist: aiofiles ==24.1.0
Requires-Dist: python-jose ==3.3.0
Provides-Extra: all
Requires-Dist: aiofiles ==24.1.0 ; extra == 'all'
Requires-Dist: aiomysql ==0.2.0 ; extra == 'all'
Requires-Dist: nest-asyncio ==1.6.0 ; extra == 'all'
Requires-Dist: cacheout ==0.14.1 ; extra == 'all'
Requires-Dist: tqdm ==4.66.4 ; extra == 'all'
Requires-Dist: requests ==2.31.0 ; extra == 'all'
Requires-Dist: python-jose ==3.3.0 ; extra == 'all'
Requires-Dist: asgiref ==3.8.1 ; extra == 'all'
Requires-Dist: minio ==7.1.17 ; extra == 'all'
Requires-Dist: pandas ==2.0.3 ; extra == 'all'
Requires-Dist: python-memcached ==1.62 ; extra == 'all'
Requires-Dist: sqlalchemy[asyncio] ==2.0.20 ; extra == 'all'
Requires-Dist: redis >=4.5.4 ; extra == 'all'
Requires-Dist: openpyxl ==3.0.10 ; extra == 'all'
Requires-Dist: python-dateutil ==2.8.2 ; extra == 'all'
Requires-Dist: aiohttp ==3.9.5 ; extra == 'all'
Requires-Dist: pydantic <3,>=2.1.1 ; extra == 'all'
Requires-Dist: loguru <0.8,>=0.7.0 ; extra == 'all'
Provides-Extra: cache-proxy
Requires-Dist: redis >=4.5.4 ; extra == 'cache-proxy'
Requires-Dist: python-memcached ==1.62 ; extra == 'cache-proxy'
Requires-Dist: cacheout ==0.14.1 ; extra == 'cache-proxy'
Provides-Extra: db-orm
Requires-Dist: sqlalchemy[asyncio] ==2.0.20 ; extra == 'db-orm'
Requires-Dist: aiomysql ==0.2.0 ; extra == 'db-orm'
Provides-Extra: db-redis
Requires-Dist: redis >=4.5.4 ; extra == 'db-redis'
Provides-Extra: excel-tools
Requires-Dist: pandas ==2.0.3 ; extra == 'excel-tools'
Requires-Dist: openpyxl ==3.0.10 ; extra == 'excel-tools'
Provides-Extra: minio
Requires-Dist: minio ==7.1.17 ; extra == 'minio'
Provides-Extra: test
Requires-Dist: pytest ==7.3.1 ; extra == 'test'
Requires-Dist: pytest-mock ==3.14.0 ; extra == 'test'
Requires-Dist: pytest-asyncio ==0.23.8 ; extra == 'test'
